DownloadJenkinsBuildLog/__init__.py
DownloadJenkinsBuildLog/downloader.py
download_jenkins_build_log-0.0.1a7.dist-info/LICENSE
download_jenkins_build_log-0.0.1a7.dist-info/METADATA
download_jenkins_build_log-0.0.1a7.dist-info/WHEEL
download_jenkins_build_log-0.0.1a7.dist-info/entry_points.txt
download_jenkins_build_log-0.0.1a7.dist-info/top_level.txt
download_jenkins_build_log-0.0.1a7.dist-info/RECORD
