Metadata-Version: 2.1
Name: download-jenkins-build-log
Version: 0.0.1a7
Summary: Command-line utility for downloading Jenkins job console logs
Home-page: https://github.com/bertold/download-jenkins-build-log
Author: Bertold Kolics
Author-email: bertold@qualityraven.com
License: UNKNOWN
Project-URL: Source, https://github.com/bertold/download-jenkins-build-log
Keywords: Jenkins logs tools
Platform: UNKNOWN
Classifier: Programming Language :: Python :: 3
Classifier: License :: OSI Approved :: Apache Software License
Classifier: Operating System :: OS Independent
Classifier: Development Status :: 3 - Alpha
Classifier: Topic :: Software Development :: Build Tools
Requires-Python: >=3
Requires-Dist: requests
